rustic_ai/testing/__init__.py
rustic_ai/testing/agent_ext/__init__.py
rustic_ai/testing/agent_ext/base_test_kvstore.py
rustic_ai/testing/agents/__init__.py
rustic_ai/testing/agents/sample_agents.py
rustic_ai/testing/agents/simple_agent.py
rustic_ai/testing/execution/__init__.py
rustic_ai/testing/execution/base_test_integration.py
rustic_ai/testing/execution/integration_agents.py
rustic_ai/testing/helpers.py
rustic_ai/testing/messaging/__init__.py
rustic_ai/testing/messaging/base_test_backend.py
rustic_ai/testing/messaging/base_test_messaging.py
rustic_ai/testing/state/__init__.py
rustic_ai/testing/state/base_test_state_mgr.py
rusticai_testing-1.0.0.dist-info/METADATA
rusticai_testing-1.0.0.dist-info/WHEEL
rusticai_testing-1.0.0.dist-info/RECORD
